dicomslide/__init__.py
dicomslide/_channel.py
dicomslide/enum.py
dicomslide/image.py
dicomslide/matrix.py
dicomslide/openslide.py
dicomslide/pyramid.py
dicomslide/slide.py
dicomslide/tile.py
dicomslide/utils.py
dicomslide/version.py
dicomslide-0.7.2.dist-info/LICENSE
dicomslide-0.7.2.dist-info/METADATA
dicomslide-0.7.2.dist-info/WHEEL
dicomslide-0.7.2.dist-info/top_level.txt
dicomslide-0.7.2.dist-info/RECORD
