Metadata-Version: 2.1
Name: dicomslide
Version: 0.7.2
Summary: Library for reading whole slide images and derived information in DICOM format.
Home-page: https://github.com/herrmannlab/dicomslide
Author: Markus D. Herrmann
Maintainer: Markus D. Herrmann
License: MIT
Platform: Linux
Platform: MacOS
Platform: Windows
Classifier: Operating System :: MacOS
Classifier: Operating System :: Microsoft :: Windows
Classifier: Operating System :: POSIX :: Linux
Classifier: License :: OSI Approved :: MIT License
Classifier: Intended Audience :: Science/Research
Classifier: Topic :: Multimedia :: Graphics
Classifier: Topic :: Scientific/Engineering :: Information Analysis
Classifier: Programming Language :: Python :: 3
Classifier: Programming Language :: Python :: 3.6
Classifier: Programming Language :: Python :: 3.7
Classifier: Programming Language :: Python :: 3.8
Classifier: Programming Language :: Python :: 3.9
Classifier: Programming Language :: Python :: 3.10
Classifier: Programming Language :: Python :: 3.11
Classifier: Development Status :: 4 - Beta
Requires-Python: >=3.6
License-File: LICENSE
Requires-Dist: dicomweb-client >=0.56.2
Requires-Dist: highdicom >=0.16.0
Requires-Dist: numpy >=1.19
Requires-Dist: pydicom >=2.3.0
Requires-Dist: scipy >=1.0
